jaguar_haystack/LICENSE
jaguar_haystack/README.md
jaguar_haystack/__init__.py
jaguar_haystack/jaguar.py
jaguar_haystack/retriever.py
jaguar_haystack-3.4.2.5.data/data/jaguardb/LICENSE
jaguar_haystack-3.4.2.5.data/data/jaguardb/README.md
jaguar_haystack-3.4.2.5.data/data/jaguardb/jaguar.py
jaguar_haystack-3.4.2.5.data/data/jaguardb/retriever.py
jaguar_haystack-3.4.2.5.dist-info/METADATA
jaguar_haystack-3.4.2.5.dist-info/WHEEL
jaguar_haystack-3.4.2.5.dist-info/top_level.txt
jaguar_haystack-3.4.2.5.dist-info/RECORD
