Metadata-Version: 2.1
Name: jaguar-haystack
Version: 3.4.2.5
Summary: Jaguar document store for Haystack framework
Home-page: http://www.jaguardb.com
Author: JaguarDB
License: Apache 2.0
Platform: UNKNOWN
Requires-Python: >=3.0
